{"ID":"645za146-04ea-4r8e-9bd3-fveef7f9f8c0","ERPRefDocNumber":"SOU2022000000537","UUID":"73DB0E7A-95F9-4BB4-9104-F53B13BC4C27","IssueDate":"2022-03-30T00:00:00.000Z","IssueTime":"1970-01-01T00:25:09.117Z","InvoiceType":"SATIS","CurrencyCode":"TRY","ProfileID":"EARSIVFATURA","ExchangeRate":null,"Despatches":[],"Notes":[],"Order":{},"Parties":[{"Type":2,"Website":null,"Name":"SAFİR HIRDAVAT ORMAN ÜRÜNLERİ TAR.GIDA İNŞ.TUR.SAN.VE LTD.ŞTİ.","Address":"BOĞAZİÇİ CD. NO:79","Country":["TÜRKİYE","TÜRKİYE"],"District":"KONAK","City":"İZMİR","TaxOffice":"ŞİRİNYER V.D.","PhoneNumber":"232457 22 20","FaxNumber":"232457 22 30","PostalCode":null,"Mail":"","ERPPartyID":"2f4z59df-1a1c-4r32-9042-2va52f541d6b","Identities":[{"SchemaID":"VKN","Value":"7370509372"}]}],"InvoiceLines":[{"ERPLineID":"5bez158f-d9cf-4r2a-a1ab-2v2c1ce00010","Quantity":3,"Price":271.1864,"UnitCode":"C62","Name":"HAMMADDE","TaxAmount":146.44,"Taxes":[{"TaxableAmount":813.56,"TaxAmount":146.44,"TaxPercent":18,"TaxCode":"0015","TaxExemptionReasonCode":0,"CurrencyCode":"TRY"}],"Allowances":[]}],"Taxes":[{"TaxableAmount":813.56,"TaxAmount":146.44,"TaxPercent":18,"TaxCode":"0015","CurrencyCode":"TRY"}],"TaxAmount":146.44,"Allowance":{"ChargeIndicator":false,"Amount":0,"CurrencyCode":"TRY"},"Monetary":{"LineExtensionAmount":813.5591999999999,"TaxExclusiveAmount":813.56,"TaxInclusiveAmount":959.9992,"AllowanceChargeAmount":0,"PayableAmount":959.9992,"CurrencyCode":"TRY"},"Alias":null,"SystemInvTypeCode":2,"XSLTCode":2}